shanbay/__init__.py
shanbay/api.py
shanbay/exceptions.py
shanbay/message.py
shanbay/team.py
shanbay-0.3.6.dist-info/DESCRIPTION.rst
shanbay-0.3.6.dist-info/METADATA
shanbay-0.3.6.dist-info/metadata.json
shanbay-0.3.6.dist-info/RECORD
shanbay-0.3.6.dist-info/top_level.txt
shanbay-0.3.6.dist-info/WHEEL
