Metadata-Version: 2.0
Name: shanbay
Version: 0.3.6
Summary: Python wrapper for shanbay.com
Home-page: https://github.com/mozillazg/python-shanbay
Author: mozillazg
Author-email: mozillazg101@gmail.com
License: MIT
Keywords: shanbay,扇贝网
Platform: UNKNOWN
Classifier: Development Status :: 5 - Production/Stable
Classifier: Intended Audience :: Developers
Classifier: License :: OSI Approved :: MIT License
Classifier: Operating System :: OS Independent
Classifier: Programming Language :: Python
Classifier: Programming Language :: Python :: 2
Classifier: Programming Language :: Python :: 2.6
Classifier: Programming Language :: Python :: 2.7
Classifier: Programming Language :: Python :: 3
Classifier: Programming Language :: Python :: 3.3
Classifier: Programming Language :: Python :: 3.4
Classifier: Programming Language :: Python :: 3.5
Classifier: Topic :: Utilities
Requires-Dist: requests (>=2.9.0)
Requires-Dist: beautifulsoup4
Requires-Dist: html5lib
Requires-Dist: requests-oauthlib
